__CryptoLib.cpython-311-x86_64-linux-gnu.so
krptn-0.8.6.dist-info/WHEEL
krptn-0.8.6.dist-info/LICENSE
krptn-0.8.6.dist-info/RECORD
krptn-0.8.6.dist-info/top_level.txt
krptn-0.8.6.dist-info/METADATA
krypton/base.py
krypton/__init__.py
krypton/basic.py
krypton/_load.py
krypton/__main__.py
krypton/auth/_utils.py
krypton/auth/factors.py
krypton/auth/__init__.py
krypton/auth/users/userModel.py
krypton/auth/users/bases.py
krypton/auth/users/__init__.py
krypton/auth/users/userModelBaseAuth.py
krypton/auth/users/userModelMFAAuth.py
krypton/auth/django/types.py
krypton/auth/django/middleware.py
krypton/auth/django/__init__.py
krypton/auth/django/users.py
