Metadata-Version: 2.1
Name: krptn
Version: 0.8.6
Summary: IAM and data encryption at rest
Author-email: Krptn Project <contact@krptn.dev>
Project-URL: Homepage, https://www.krptn.dev/
Project-URL: Documentation, https://docs.krptn.dev/
Project-URL: GitHub, https://github.com/krptn/krypton/
Project-URL: Bug Tracker, https://github.com/krptn/krypton/issues
Classifier: License :: OSI Approved :: Apache Software License
Classifier: Operating System :: OS Independent
Classifier: Intended Audience :: Developers
Classifier: Intended Audience :: System Administrators
Classifier: Topic :: Security
Classifier: Topic :: Security :: Cryptography
Classifier: Framework :: Django
Classifier: Framework :: Flask
Requires-Python: >3.9
License-File: LICENSE
Requires-Dist: SQLAlchemy >=1.4.0
Requires-Dist: webauthn >=1.6.0
Provides-Extra: django
Requires-Dist: django ; extra == 'django'
Provides-Extra: flask
Requires-Dist: flask ; extra == 'flask'
Provides-Extra: mssql
Requires-Dist: pyodbc ; extra == 'mssql'
Provides-Extra: mysql
Requires-Dist: mysqlclient ; extra == 'mysql'
Provides-Extra: postgresql
Requires-Dist: psycopg2 ; extra == 'postgresql'
Provides-Extra: tests
Requires-Dist: django ; extra == 'tests'
